{
  "name": "Readinza Source",
  "identifier": "com.github.readinza.source",
  "apps": [
    {
      "name": "Readinza",
      "bundleIdentifier": "com.github.readinza.Readinza",
      "developerName": "Readinza",
      "version": "26.0.13",
      "versionDate": "2025-09-11T22:46:44Z",
      "versionDescription": "Improvements and fixes.",
      "downloadURL": "https://readinza.github.io/files/Readinza.ipa",
      "localizedDescription": "Readinza",
      "iconURL": "https://readinza.github.io/files/readinza.png",
      "tintColor": "018084",
      "size": 13082949,
      "screenshotURLs": [],
      "permissions": {
        "entitlements": [
          "get-task-allow"
        ]
      }
    }
  ]
}
